odoo/addons/web_company_logo/README.rst
odoo/addons/web_company_logo/__init__.py
odoo/addons/web_company_logo/__manifest__.py
odoo/addons/web_company_logo/controllers/__init__.py
odoo/addons/web_company_logo/controllers/main.py
odoo/addons/web_company_logo/readme/CONFIGURE.md
odoo/addons/web_company_logo/readme/DESCRIPTION.md
odoo/addons/web_company_logo/static/description/icon.png
odoo/addons/web_company_logo/static/description/index.html
odoo/addons/web_company_logo/static/src/css/menu.css
odoo/addons/web_company_logo/static/src/js/menu.esm.js
odoo/addons/web_company_logo/static/src/xml/menu.xml
odoo_addon_web_company_logo-17.0.1.1.0.dist-info/METADATA
odoo_addon_web_company_logo-17.0.1.1.0.dist-info/WHEEL
odoo_addon_web_company_logo-17.0.1.1.0.dist-info/top_level.txt
odoo_addon_web_company_logo-17.0.1.1.0.dist-info/RECORD
