Metadata-Version: 2.1
Name: odoo-addon-web_company_logo
Version: 17.0.1.1.0
Requires-Python: >=3.10
Requires-Dist: odoo>=17.0a,<17.1dev
Summary: Show the company logo on top navigation bar
Home-page: https://github.com/sygel-technology/sy-web
License: AGPL-3
Author: Kareem Abuzaid, kareem.abuzaid123@gmail.com, Sygel, Odoo Community Association (OCA)
Author-email: support@odoo-community.org
Classifier: Programming Language :: Python
Classifier: Framework :: Odoo
Classifier: Framework :: Odoo :: 17.0
Classifier: License :: OSI Approved :: GNU Affero General Public License v3
